scrapy_azure/__init__.py
scrapy_azure/addon.py
scrapy_azure/feedstorage.py
scrapy_azure-0.2.0.dist-info/METADATA
scrapy_azure-0.2.0.dist-info/WHEEL
scrapy_azure-0.2.0.dist-info/licenses/LICENSE.txt
scrapy_azure-0.2.0.dist-info/RECORD
